bigquery_auth/__init__.py
bigquery_auth/bigquery_auth.py
5x_google_bigquery_auth_manager-0.1.2.dist-info/METADATA
5x_google_bigquery_auth_manager-0.1.2.dist-info/WHEEL
5x_google_bigquery_auth_manager-0.1.2.dist-info/top_level.txt
5x_google_bigquery_auth_manager-0.1.2.dist-info/RECORD
