Metadata-Version: 2.2
Name: 5x-google-bigquery-auth-manager
Version: 0.1.2
Summary: A simple Python library for creating a Google BigQuery client using either an access token or a service account JSON file.
Home-page: https://github.com/5x-Platform/5x-nextgen-python-libraries.git
Author: 5X
Author-email: support@5x.co
Classifier: Programming Language :: Python :: 3.8
Classifier: Programming Language :: Python :: 3.9
Classifier: Programming Language :: Python :: 3.10
Classifier: Programming Language :: Python :: 3.11
Classifier: Programming Language :: Python :: 3.12
Classifier: License :: OSI Approved :: MIT License
Classifier: Operating System :: OS Independent
Classifier: Development Status :: 3 - Alpha
Classifier: Intended Audience :: Developers
Classifier: Topic :: Software Development :: Libraries :: Python Modules
Requires-Python: >=3.8
Requires-Dist: google-api-core
Requires-Dist: google-cloud-bigquery
Requires-Dist: google-cloud-bigquery-storage
Requires-Dist: db-dtypes
Dynamic: author
Dynamic: author-email
Dynamic: classifier
Dynamic: description
Dynamic: description-content-type
Dynamic: home-page
Dynamic: requires-dist
Dynamic: requires-python
Dynamic: summary
